MANIFEST.in
README.rst
setup.py
osuosl_hieroglyph_theme/__init__.py
osuosl_hieroglyph_theme.egg-info/PKG-INFO
osuosl_hieroglyph_theme.egg-info/SOURCES.txt
osuosl_hieroglyph_theme.egg-info/dependency_links.txt
osuosl_hieroglyph_theme.egg-info/not-zip-safe
osuosl_hieroglyph_theme.egg-info/requires.txt
osuosl_hieroglyph_theme.egg-info/top_level.txt
osuosl_hieroglyph_theme/osuosl/theme.conf
osuosl_hieroglyph_theme/osuosl/static/logo.png
osuosl_hieroglyph_theme/osuosl/static/osu-tag.png
osuosl_hieroglyph_theme/osuosl/static/osuosl.css_t