Metadata-Version: 1.0
Name: osuosl-hieroglyph-theme
Version: 0.9
Summary: Slides theme for  the OSU Open Source Lab
Home-page: https://github.com/osuosl/osuosl_hieroglyph_theme
Author: Lucy Wyman
Author-email: lucyw@osuosl.org
License: UNKNOWN
Keywords: hieroglyph extension theme
Platform: UNKNOWN
